config/__init__.py
config/config.py
wsbtrading/__init__.py
wsbtrading/data_io/__init__.py
wsbtrading/data_io/data_io.py
wsbtrading/data_io/tests/__init__.py
wsbtrading/data_io/tests/test_data_io.py
wsbtrading/instrumentation/__init__.py
wsbtrading/instrumentation/instrumentation.py
wsbtrading/maths/__init__.py
wsbtrading/maths/maths.py
wsbtrading/maths/tests/__init__.py
wsbtrading/maths/tests/test_maths.py
wsbtrading/model/__init__.py
wsbtrading/model/ttm_squeeze/__init__.py
wsbtrading/model/ttm_squeeze/ttm_squeeze.py
wsbtrading/order/__init__.py
wsbtrading/order/account.py
wsbtrading/order/config.py
wsbtrading/order/order.py
wsbtrading/order/utils.py
wsbtrading/tests/__init__.py
wsbtrading/utils/__init__.py
wsbtrading/utils/dates.py
wsbtrading/utils/tests/__init__.py
wsbtrading/utils/tests/test_dates.py
wsbtrading-1.0.0a14.dist-info/LICENSE
wsbtrading-1.0.0a14.dist-info/METADATA
wsbtrading-1.0.0a14.dist-info/WHEEL
wsbtrading-1.0.0a14.dist-info/top_level.txt
wsbtrading-1.0.0a14.dist-info/RECORD
